virtualwatts/__init__.py
virtualwatts/__main__.py
virtualwatts/actor.py
virtualwatts/context.py
virtualwatts/report/__init__.py
virtualwatts-0.1.1.dist-info/LICENSE
virtualwatts-0.1.1.dist-info/METADATA
virtualwatts-0.1.1.dist-info/WHEEL
virtualwatts-0.1.1.dist-info/top_level.txt
virtualwatts-0.1.1.dist-info/RECORD
