Metadata-Version: 2.1
Name: virtualwatts
Version: 0.1.1
Summary: VirtualWatts is a formula for a  software-defined power meter based on the PowerAPI framework.
Home-page: UNKNOWN
Author: Lauric Desauw
License: MIT
Keywords: energy,powerapi,containers,performance counters,power meter
Platform: UNKNOWN
Classifier: Programming Language :: Python :: 3.7
Classifier: License :: OSI Approved :: MIT License
Requires-Python: >=3.7
Requires-Dist: powerapi[influxdb,mongodb,opentsdb,prometheus] (>=1.0.2)
